{
  "update_type": "SNAPSHOT",
  "updates": [
    {
      "timestamp": 291700,
      "poses": {
        "/vehicle_pose": {
          "timestamp": 291700,
          "map_origin": {
            "longitude": 13.349286999999999,
            "latitude": 52.5149987,
            "altitude": 0
          },
          "position": [
            0,
            0,
            0
          ],
          "orientation": [
            0,
            0,
            126.33354000000003
          ]
        }
      }
    }
  ]
}