{
  "update_type": "SNAPSHOT",
  "updates": [
    {
      "timestamp": 294300,
      "poses": {
        "/vehicle_pose": {
          "timestamp": 294300,
          "map_origin": {
            "longitude": 13.349273799999999,
            "latitude": 52.514984999999996,
            "altitude": 0
          },
          "position": [
            0,
            0,
            0
          ],
          "orientation": [
            0,
            0,
            124.18860000000001
          ]
        }
      }
    }
  ]
}