{
  "update_type": "SNAPSHOT",
  "updates": [
    {
      "timestamp": 37500,
      "poses": {
        "/vehicle_pose": {
          "timestamp": 37500,
          "map_origin": {
            "longitude": 13.3293822,
            "latitude": 52.513087,
            "altitude": 0
          },
          "position": [
            0,
            0,
            0
          ],
          "orientation": [
            0,
            0,
            -5.8924399999999935
          ]
        }
      }
    }
  ]
}