{
  "update_type": "SNAPSHOT",
  "updates": [
    {
      "timestamp": 111833,
      "poses": {
        "/vehicle_pose": {
          "timestamp": 111833,
          "map_origin": {
            "longitude": 13.337571899999999,
            "latitude": 52.5136396,
            "altitude": 0
          },
          "position": [
            0,
            0,
            0
          ],
          "orientation": [
            0,
            0,
            -0.9573699999999974
          ]
        }
      }
    }
  ]
}